tqdmpromproxy/__init__.py
tqdmpromproxy/bucket.py
tqdmpromproxy/manager.py
tqdmpromproxy/metric_server.py
tqdmpromproxy/monitor.py
tqdmpromproxy/proxy.py
tqdmpromproxy/snapshot.py
tqdm_prometheus_exporter-0.1.15.dist-info/METADATA
tqdm_prometheus_exporter-0.1.15.dist-info/WHEEL
tqdm_prometheus_exporter-0.1.15.dist-info/RECORD
