Metadata-Version: 2.4
Name: tqdm-prometheus-exporter
Version: 0.1.15
Summary: Echo tqdm progress to a prometheus endpoint
Project-URL: Homepage, https://github.com/arrowed/tqdm-prometheus-exporter
Project-URL: Issues, https://github.com/arrowed/tqdm-prometheus-exporter/issues
Author-email: arrowed <arrowed@arrowed.org>
License-Expression: MIT
Classifier: Operating System :: OS Independent
Classifier: Programming Language :: Python :: 3
Requires-Python: >=3.8
Requires-Dist: bottle>=0.13.0
Requires-Dist: jsonpickle>=2.0.0
Requires-Dist: pytest-cov>=3.0.0
Requires-Dist: pytest-html>=3.0.0
Requires-Dist: pytest>=8.3.4
Requires-Dist: requests>=2.26.0
Requires-Dist: tqdm>=4.67.1
